pyenc/__init__.py
pyenc/pyenc.py
pyenc-2.0.0.dist-info/LICENSE
pyenc-2.0.0.dist-info/METADATA
pyenc-2.0.0.dist-info/WHEEL
pyenc-2.0.0.dist-info/entry_points.txt
pyenc-2.0.0.dist-info/top_level.txt
pyenc-2.0.0.dist-info/RECORD
