Metadata-Version: 2.1
Name: pyenc
Version: 2.0.0
Summary: Python3 Script Encrypt
Home-page: https://github.com/AKXVAU
Author: AKXVAU
Author-email: akxvau@gmail.com
License: MIT
Keywords: hacker,spam,tool,sms,pyenc,call,prank,termux,hack,Py Encrypt,Encryptor,AKXVAU
Classifier: Development Status :: 4 - Beta
Classifier: Intended Audience :: Developers
Classifier: Topic :: Software Development :: Libraries :: Python Modules
Classifier: License :: OSI Approved :: MIT License
Classifier: Programming Language :: Python :: 3
Classifier: Operating System :: OS Independent
Classifier: Environment :: Console
Requires-Python: >=3.9
License-File: LICENSE
Requires-Dist: pip
